{"created_at": "Wed Oct 19 02:51:03 +0000 2011", "favorited": false, "hashtags": ["google"], "id": 126490516186595328, "id_str": "126490516186595328", "lang": "de", "retweeted": false, "source": "web", "text": "SO Hinweis: kostenlose SEO Videos  http://t.co/pwldYXVE #google", "truncated": false, "urls": {"http://t.co/pwldYXVE": "http://nextgenerationseo.de"}, "user": {"created_at": "Tue Sep 21 16:43:17 +0000 2010", "description": "Wer will nochmal, wer hat noch nicht? Gibt immer nur eine Position 1 ... daf\u00fcr aber viel :)", "followers_count": 3275, "friends_count": 3705, "id": 193359699, "lang": "de", "listed_count": 48, "location": "Deutschland", "name": "Tom Breuer", "profile_background_color": "8B542B", "profile_background_image_url": "http://abs.twimg.com/images/themes/theme8/bg.gif", "profile_background_tile": false, "profile_image_url": "https://pbs.twimg.com/profile_images/1128308500/Scary_Math_Microstock_normal.jpg", "profile_link_color": "9D582E", "profile_sidebar_fill_color": "EADEAA", "profile_text_color": "333333", "protected": false, "screen_name": "echte_seo_tipps", "statuses_count": 12289, "url": "http://t.co/RxdWALXpq2"}}
