{"created_at": "Wed Oct 19 03:55:10 +0000 2011", "favorited": false, "hashtags": ["TechWar", "Google", "Facebook", "Apple", "Amazon"], "id": 126506651271430144, "id_str": "126506651271430144", "in_reply_to_screen_name": "dwtalker", "in_reply_to_status_id": 126487635316310016, "in_reply_to_user_id": 15457745, "lang": "en", "retweeted": false, "source": "web", "text": "@dwtalker that's some tough competition right there http://t.co/XP9LhjpR #TechWar #Google #Facebook #Apple #Amazon", "truncated": false, "urls": {"http://t.co/XP9LhjpR": "http://bit.ly/qppGbk"}, "user": {"created_at": "Mon Apr 20 03:55:21 +0000 2009", "description": "Dallas transplant in NYC - food, news & tech connoisseur  - Aspectus PR - tweets are my own", "favourites_count": 5, "followers_count": 311, "friends_count": 485, "geo_enabled": true, "id": 33413522, "lang": "en", "listed_count": 9, "location": "iPhone: 32.843842,-96.771851", "name": "Britney Schaeffer", "profile_background_color": "131516", "profile_background_image_url": "http://abs.twimg.com/images/themes/theme14/bg.gif", "profile_background_tile": true, "profile_banner_url": "https://pbs.twimg.com/profile_banners/33413522/1383681213", "profile_image_url": "https://pbs.twimg.com/profile_images/738974755/9024_1186613380683_1088730006_30643579_5814720_n_normal.jpg", "profile_link_color": "009999", "profile_sidebar_fill_color": "EFEFEF", "profile_text_color": "333333", "protected": false, "screen_name": "baschaef", "statuses_count": 1941, "time_zone": "Central Time (US & Canada)", "utc_offset": -18000}, "user_mentions": [{"id": 15457745, "name": "David Williams", "screen_name": "dwtalker"}]}
