{"created_at": "Wed Oct 19 03:35:02 +0000 2011", "favorited": false, "hashtags": ["Google"], "id": 126501582274707457, "id_str": "126501582274707457", "lang": "en", "retweeted": false, "source": "<a href=\"http://www.hootsuite.com\" rel=\"nofollow\">HootSuite</a>", "text": "#Google To Begin Encrypting Searches & Outbound Clicks By Default With SSL Search http://t.co/bf5zVm0U @searchengineland", "truncated": false, "urls": {"http://t.co/bf5zVm0U": "http://ow.ly/71CAw"}, "user": {"created_at": "Mon Jun 01 00:02:30 +0000 2009", "description": "Poetry Lover, Avid Reader, and YouTube Documentary Addict.\nUse your words. -My Mom (For Aviation News follow @AVWeekRegina )", "favourites_count": 5417, "followers_count": 31475, "friends_count": 21025, "id": 43784863, "lang": "en", "listed_count": 318, "location": "Chicago, IL", "name": "Regina Kenney", "profile_background_color": "C0DEED", "profile_background_image_url": "http://pbs.twimg.com/profile_background_images/812462617/e0f3305cf04db0b60cc40f4ced656473.jpeg", "profile_background_tile": true, "profile_banner_url": "https://pbs.twimg.com/profile_banners/43784863/1391117943", "profile_image_url": "https://pbs.twimg.com/profile_images/3369135623/d1f4a49755e404fbe2acebc1bacc2c92_normal.jpeg", "profile_link_color": "0084B4", "profile_sidebar_fill_color": "DDEEF6", "profile_text_color": "333333", "protected": false, "screen_name": "Regina_Kenney", "statuses_count": 7829, "time_zone": "Mountain Time (US & Canada)", "utc_offset": -21600}}
