{"created_at": "Wed Oct 19 03:49:21 +0000 2011", "favorited": false, "hashtags": ["SmarterPhone", "ICS", "google"], "id": 126505187752943616, "id_str": "126505187752943616", "lang": "en", "retweeted": false, "source": "<a href=\"https://about.twitter.com/products/tweetdeck\" rel=\"nofollow\">TweetDeck</a>", "text": "Mmm... #SmarterPhone RT @Android: Introducing Ice Cream Sandwich, the delicious new version of Android: http://t.co/AXl2K1Gs #ICS #google", "truncated": false, "urls": {"http://t.co/AXl2K1Gs": "http://bit.ly/pO1CmP"}, "user": {"created_at": "Thu May 22 23:07:01 +0000 2008", "description": "IBM Technologist on: Innovation, Social Business, Collective Intelligence, Future of Work, Analytics, Customer Experience. Boston fan/native. Thoughts are mine.", "favourites_count": 2466, "followers_count": 1749, "friends_count": 1617, "geo_enabled": true, "id": 14874721, "lang": "en", "listed_count": 153, "location": "NYC area", "name": "Bob Pulver", "profile_background_color": "022330", "profile_background_image_url": "http://abs.twimg.com/images/themes/theme15/bg.png", "profile_background_tile": false, "profile_banner_url": "https://pbs.twimg.com/profile_banners/14874721/1348054178", "profile_image_url": "https://pbs.twimg.com/profile_images/378800000744699829/d5997033cb8dbf09d4333c3875060496_normal.jpeg", "profile_link_color": "0084B4", "profile_sidebar_fill_color": "C0DFEC", "profile_text_color": "333333", "protected": false, "screen_name": "pulvereyes", "statuses_count": 5649, "time_zone": "Quito", "url": "http://t.co/6WOhgeToqO", "utc_offset": -18000}, "user_mentions": [{"id": 382267114, "name": "Android", "screen_name": "Android"}]}
