{"created_at": "Wed Oct 19 12:39:10 +0000 2011", "favorited": false, "hashtags": ["ERP", "Microsoft", "ax"], "id": 126638520034013184, "id_str": "126638520034013184", "lang": "es", "retweet_count": 2, "retweeted": false, "retweeted_status": {"created_at": "Wed Oct 19 11:46:59 +0000 2011", "favorited": false, "hashtags": ["ERP", "Microsoft", "ax"], "id": 126625386565087232, "id_str": "126625386565087232", "lang": "es", "retweet_count": 2, "retweeted": false, "source": "<a href=\"https://about.twitter.com/products/tweetdeck\" rel=\"nofollow\">TweetDeck</a>", "text": "RT @MuyCanal: MuyCanal: Avanade y Ferranti Computer ofrecen un #ERP basado en #Microsoft Dynamics  http://t.co/MaghjzcS @msdynamicsspain #ax", "truncated": false, "urls": {"http://t.co/MaghjzcS": "http://www.muycanal.com/?p=17987"}, "user": {"created_at": "Fri May 29 19:50:45 +0000 2009", "description": "Avanade es proveedor global de soluciones tecnol\u00f3gicas de negocio y servicios gestionados creada por Microsoft y Accenture", "favourites_count": 13, "followers_count": 856, "friends_count": 475, "id": 43395434, "lang": "es", "listed_count": 54, "location": "Madrid; Barcelona; M\u00e1laga", "name": "Avanade Spain", "profile_background_color": "EEEEEE", "profile_background_image_url": "http://pbs.twimg.com/profile_background_images/534697246/avanade_twitter_background-eeeeee.jpg", "profile_background_tile": false, "profile_image_url": "https://pbs.twimg.com/profile_images/2162119256/avanade-twitter-profile_normal.jpg", "profile_link_color": "FF5800", "profile_sidebar_fill_color": "F5F5F5", "profile_text_color": "333333", "protected": false, "screen_name": "AvanadeSpain", "statuses_count": 2559, "time_zone": "Madrid", "url": "http://t.co/8iVFWYfaQj", "utc_offset": 7200}, "user_mentions": [{"id": 377257161, "name": "MuyCanal", "screen_name": "MuyCanal"}, {"id": 301335113, "name": "MSDynamicsSpain", "screen_name": "MSDynamicsSpain"}]}, "source": "<a href=\"http://mobile.twitter.com\" rel=\"nofollow\">Mobile Web</a>", "text": "RT @AvanadeSpain: RT @MuyCanal: MuyCanal: Avanade y Ferranti Computer ofrecen un #ERP basado en #Microsoft Dynamics  http://t.co/Maghjzc ...", "truncated": false, "urls": {"http://t.co/MaghjzcS": "http://www.muycanal.com/?p=17987"}, "user": {"created_at": "Mon Apr 09 11:20:19 +0000 2007", "description": "Father, developer, tech, MVP Visual Studio ALM, Innovation Manager in Avanade", "favourites_count": 20, "followers_count": 1398, "friends_count": 370, "geo_enabled": true, "id": 3889921, "lang": "es", "listed_count": 104, "location": "Madrid, Spain", "name": "Bruno Capuano", "profile_background_color": "352726", "profile_background_image_url": "http://pbs.twimg.com/profile_background_images/175861127/twilk_background_4cf15f925eff8.jpg", "profile_background_tile": true, "profile_banner_url": "https://pbs.twimg.com/profile_banners/3889921/1367147258", "profile_image_url": "https://pbs.twimg.com/profile_images/3585272650/192a868e0cac47d8b3681a7e55d0e784_normal.jpeg", "profile_link_color": "D02B55", "profile_sidebar_fill_color": "99CC33", "profile_text_color": "3E4415", "protected": false, "screen_name": "elbruno", "statuses_count": 6712, "time_zone": "Madrid", "url": "http://t.co/TZUZRJAwOd", "utc_offset": 7200}, "user_mentions": [{"id": 43395434, "name": "Avanade Spain", "screen_name": "AvanadeSpain"}, {"id": 377257161, "name": "MuyCanal", "screen_name": "MuyCanal"}, {"id": 301335113, "name": "MSDynamicsSpain", "screen_name": "MSDynamicsSpain"}]}
