{"created_at": "Wed Oct 19 15:17:51 +0000 2011", "favorited": false, "hashtags": ["Microsoft", "Web2", "Yahoo"], "id": 126678454639927297, "id_str": "126678454639927297", "lang": "en", "retweeted": false, "source": "web", "text": "VIDEO: #Microsoft CEO Steve Ballmer talks at #Web2.0Summit about #Yahoo, Bing, and more.  http://t.co/YEAXVP1V", "truncated": false, "urls": {"http://t.co/YEAXVP1V": "http://www.youtube.com/watch?v=de8en0Sqy9s"}, "user": {"created_at": "Sun Jun 19 20:48:13 +0000 2011", "description": "Professionals. Not Geeks. We're a respected, full-service Information Technology provider servicing small & mid-size companies in the Washington DC region.", "followers_count": 146, "friends_count": 535, "id": 320394131, "lang": "en", "listed_count": 3, "location": "Washington DC Metro Area", "name": "HLP Associates ", "profile_background_color": "C0DEED", "profile_background_image_url": "http://abs.twimg.com/images/themes/theme1/bg.png", "profile_background_tile": false, "profile_image_url": "https://pbs.twimg.com/profile_images/1502032336/hlp.avatar_normal.JPG", "profile_link_color": "0084B4", "profile_sidebar_fill_color": "DDEEF6", "profile_text_color": "333333", "protected": false, "screen_name": "HLP_DC", "statuses_count": 277, "time_zone": "Quito", "url": "http://t.co/Tji2tlsdZ1", "utc_offset": -18000}}
