{"created_at": "Wed Oct 19 14:02:24 +0000 2011", "favorited": false, "hashtags": ["Microsoft", "WindowsPhone", "Mango", "wpdev", "wp7", "msteched"], "id": 126659465985536000, "id_str": "126659465985536000", "lang": "en", "retweet_count": 2, "retweeted": false, "source": "<a href=\"http://www.sprinklr.com\" rel=\"nofollow\">Sprinklr</a>", "text": "Join #Microsoft Experts in 1 hr for a live technical chat on #WindowsPhone #Mango Live Tiles http://t.co/YPzLTs50 #wpdev #wp7 #msteched", "truncated": false, "urls": {"http://t.co/YPzLTs50": "http://msft.it/6013RwGh"}, "user": {"created_at": "Wed Sep 17 19:36:34 +0000 2008", "description": "The premier Microsoft technology event, where IT pros and devs get deep learning on all our products.", "favourites_count": 12, "followers_count": 23959, "friends_count": 861, "id": 16335435, "lang": "en", "listed_count": 542, "location": "May 12\u201315, 2014 / Houston, TX ", "name": "TechEd NorthAmerica ", "profile_background_color": "0074C6", "profile_background_image_url": "http://pbs.twimg.com/profile_background_images/378800000087253651/d4b04a6afa0f270c132966f4379cca05.jpeg", "profile_background_tile": false, "profile_banner_url": "https://pbs.twimg.com/profile_banners/16335435/1380823063", "profile_image_url": "https://pbs.twimg.com/profile_images/378800000543087452/97af6ff7129e6465685008fa5a64f173_normal.jpeg", "profile_link_color": "0084B4", "profile_sidebar_fill_color": "005A84", "profile_text_color": "000000", "protected": false, "screen_name": "TechEd_NA", "statuses_count": 8339, "time_zone": "Pacific Time (US & Canada)", "url": "http://t.co/66FYdJbE2w", "utc_offset": -25200}}
