{"coordinates": {"coordinates": [-68.8345233, -32.8812143], "type": "Point"}, "created_at": "Wed Oct 19 22:06:03 +0000 2011", "favorited": false, "geo": {"coordinates": [-32.8812143, -68.8345233], "type": "Point"}, "hashtags": ["Microsoft"], "id": 126781181466378240, "id_str": "126781181466378240", "lang": "es", "place": {"attributes": {}, "bounding_box": {"coordinates": [[[-73.991482, -33.7510506], [-32.378186, -33.7510506], [-32.378186, 5.27192], [-73.991482, 5.27192]]], "type": "Polygon"}, "contained_within": [], "country": "Brasil", "country_code": "BR", "full_name": "Brazil", "id": "1b107df3ccc0aaa1", "name": "Brazil", "place_type": "country", "url": "https://api.twitter.com/1.1/geo/id/1b107df3ccc0aaa1.json"}, "retweeted": false, "source": "<a href=\"https://about.twitter.com/products/tweetdeck\" rel=\"nofollow\">TweetDeck</a>", "text": "#Microsoft: Una pantalla t\u00e1ctil al alcance de tu mano. http://t.co/kUAfBenM", "truncated": false, "urls": {"http://t.co/kUAfBenM": "http://bit.ly/poynd0"}, "user": {"created_at": "Thu Jul 15 20:50:47 +0000 2010", "description": "Somos una Empresa mendocina nacida en 1994, y con una larga trayectoria. Trabajamos con \u00e9xito en el \u00e1rea de la venta y distribuci\u00f3n de Materiales El\u00e9ctricos...", "favourites_count": 2, "followers_count": 166, "friends_count": 195, "geo_enabled": true, "id": 167130985, "lang": "es", "listed_count": 10, "location": "Urquiza 147, Mendoza, AR", "name": "ELECTRO URQUIZA", "profile_background_color": "1A1B1F", "profile_background_image_url": "http://pbs.twimg.com/profile_background_images/547866352/dq51qetvb1rqq08024mm.jpeg", "profile_background_tile": false, "profile_image_url": "https://pbs.twimg.com/profile_images/2205466922/01rJMadv_normal", "profile_link_color": "2FC2EF", "profile_sidebar_fill_color": "252429", "profile_text_color": "666666", "protected": false, "screen_name": "ElectroUrquiza", "statuses_count": 456, "time_zone": "Buenos Aires", "url": "http://t.co/jtCNJX8uXJ", "utc_offset": -10800}}
