{"created_at": "Wed Oct 19 21:20:57 +0000 2011", "favorited": false, "hashtags": ["Microsoft", "fb"], "id": 126769830568280065, "id_str": "126769830568280065", "lang": "es", "retweeted": false, "source": "web", "text": "Feliz por mi nombramiento #Microsoft Student Partner Nicaragua :D a trabajar por el desarrollo tecnol\u00f3gico de nuestra patria Nicaragua #fb", "truncated": false, "user": {"created_at": "Sun Jul 17 18:25:59 +0000 2011", "description": "Engineering Student Information Systems, @MovistarNi, Microsoft  Student Partner for Nicaragua, Pro Activo, FCBarcelona.", "favourites_count": 1, "followers_count": 499, "friends_count": 1950, "geo_enabled": true, "id": 337249515, "lang": "es", "listed_count": 7, "location": "Managua, Nicaragua", "name": "Oswaldo S\u00e1nchez ", "profile_background_color": "022330", "profile_background_image_url": "http://abs.twimg.com/images/themes/theme15/bg.png", "profile_background_tile": false, "profile_banner_url": "https://pbs.twimg.com/profile_banners/337249515/1396839051", "profile_image_url": "https://pbs.twimg.com/profile_images/452925431012802560/Wtz0JPsO_normal.jpeg", "profile_link_color": "000FB3", "profile_sidebar_fill_color": "C0DFEC", "profile_text_color": "333333", "protected": false, "screen_name": "oswaljavi", "statuses_count": 5024, "time_zone": "Central America", "url": "http://t.co/fHI2YfK9Hy", "utc_offset": -21600}}
