{"created_at": "Wed Oct 19 19:38:50 +0000 2011", "favorited": false, "hashtags": ["SteveBallmer", "Microsoft"], "id": 126744132763910144, "id_str": "126744132763910144", "lang": "en", "retweeted": false, "source": "<a href=\"http://www.hootsuite.com\" rel=\"nofollow\">HootSuite</a>", "text": "Reader 'Tronman' compares #SteveBallmer to an albatross around #Microsoft's neck.  Do you agree?  Join the discussion! http://t.co/Mn39R2vc", "truncated": false, "urls": {"http://t.co/Mn39R2vc": "http://twb.io/oec9ZE"}, "user": {"created_at": "Wed Aug 27 03:15:45 +0000 2008", "description": "The Global Leader In Business Technology Media", "followers_count": 4029, "friends_count": 16, "id": 16007142, "lang": "en", "listed_count": 241, "location": "San Francisco, CA", "name": "TechWeb", "profile_background_color": "000000", "profile_background_image_url": "http://pbs.twimg.com/profile_background_images/3113897/bg.jpg", "profile_background_tile": false, "profile_image_url": "https://pbs.twimg.com/profile_images/996331408/ubm-techweb-web_twitter_b_normal.png", "profile_link_color": "0099B9", "profile_sidebar_fill_color": "95E8EC", "profile_text_color": "3C3940", "protected": false, "screen_name": "techweb", "statuses_count": 21092, "time_zone": "Pacific Time (US & Canada)", "url": "http://t.co/XbMtSiw2rD", "utc_offset": -25200}}
