{"created_at": "Thu Oct 20 03:54:02 +0000 2011", "favorited": false, "hashtags": ["TWITTER"], "id": 126868751533617152, "id_str": "126868751533617152", "lang": "en", "retweet_count": 1, "retweeted": false, "retweeted_status": {"created_at": "Wed Oct 19 23:30:51 +0000 2011", "favorited": false, "hashtags": ["TWITTER"], "id": 126802522047393792, "id_str": "126802522047393792", "lang": "en", "retweet_count": 1, "retweeted": false, "source": "<a href=\"http://lazyshoutout.com\" rel=\"nofollow\">LazyShoutOut</a>", "text": "SIMPLY DA BEST ON #TWITTER MY TWEEPS @Mui_Dziak @Ecofriendly211 @wstein @imCHOKOLATEwhoU @SoDear2MyHeart @sscoop4 @PyrexPress", "truncated": false, "user": {"created_at": "Tue Oct 13 02:47:15 +0000 2009", "description": "Sup? 516 362 1957 I am Producer 9-0. Movie scripts, Video, Audio, Designer, Writer, Author, Father, comedian, Religious, American, Husband and more #BogardThat", "favourites_count": 155, "followers_count": 529304, "friends_count": 135119, "id": 81994188, "lang": "en", "listed_count": 646, "location": "SHOW ME STATE", "name": "Official Page of 9-0", "profile_background_color": "9AE4E8", "profile_background_image_url": "http://abs.twimg.com/images/themes/theme16/bg.gif", "profile_background_tile": false, "profile_banner_url": "https://pbs.twimg.com/profile_banners/81994188/1396552819", "profile_image_url": "https://pbs.twimg.com/profile_images/452327980191064065/ZvUwfHSA_normal.jpeg", "profile_link_color": "0084B4", "profile_sidebar_fill_color": "DDFFCC", "profile_text_color": "333333", "protected": false, "screen_name": "nine_oh", "statuses_count": 371081, "time_zone": "Central Time (US & Canada)", "url": "https://t.co/UQraBPwsXR", "utc_offset": -18000}, "user_mentions": [{"id": 367576602, "name": "Mui _Dziak", "screen_name": "Mui_Dziak"}, {"id": 373240457, "name": "Ecofriendly211", "screen_name": "Ecofriendly211"}, {"id": 22589921, "name": " Doc Nirvana  ", "screen_name": "wstein"}, {"id": 327038661, "name": "\u2665  \u0e3fOSS\u0e3fITCH\u20a6ATION \u2665", "screen_name": "imCHOKOLATEwhoU"}, {"id": 19250651, "name": "Terri Weaver", "screen_name": "SoDear2MyHeart"}, {"id": 16506186, "name": "#LowSec", "screen_name": "sscoop4"}, {"id": 43924344, "name": "R0M0", "screen_name": "PyrexPress"}]}, "source": "<a href=\"http://twidroyd.com\" rel=\"nofollow\">Twidroyd for Android</a>", "text": "RT @nine_oh: SIMPLY DA BEST ON #TWITTER MY TWEEPS @Mui_Dziak @Ecofriendly211 @wstein @imCHOKOLATEwhoU @SoDear2MyHeart @sscoop4 @PyrexPress", "truncated": false, "user": {"created_at": "Thu Jun 30 22:10:51 +0000 2011", "description": "#TEAMCHOKOLATE #BELLAGIRLS\n\n\nFK THIS WORLD WIT THE\n DEVILS DICK\n               MARRIED TO \n      \u2665 @LILBITKNWSHEBAD \u2665\n\nInnocent Til Proven Guilty\n* ROLL UP*", "favourites_count": 367, "followers_count": 4944, "friends_count": 4710, "id": 327038661, "lang": "en", "listed_count": 221, "location": "makinuglyhoeslookgood\u2605", "name": "\u2665  \u0e3fOSS\u0e3fITCH\u20a6ATION \u2665", "profile_background_color": "C0DEED", "profile_background_image_url": "http://pbs.twimg.com/profile_background_images/361749766/kkk.jpg", "profile_background_tile": false, "profile_banner_url": "https://pbs.twimg.com/profile_banners/327038661/1395442372", "profile_image_url": "https://pbs.twimg.com/profile_images/3543754642/d19905f57dbb0859da2467fee92baade_normal.jpeg", "profile_link_color": "0084B4", "profile_sidebar_fill_color": "DDEEF6", "profile_text_color": "333333", "protected": false, "screen_name": "imCHOKOLATEwhoU", "statuses_count": 27482, "time_zone": "Pacific Time (US & Canada)", "url": "http://t.co/1QOqSQutda", "utc_offset": -25200}, "user_mentions": [{"id": 81994188, "name": "Official Page of 9-0", "screen_name": "nine_oh"}, {"id": 367576602, "name": "Mui _Dziak", "screen_name": "Mui_Dziak"}, {"id": 373240457, "name": "Ecofriendly211", "screen_name": "Ecofriendly211"}, {"id": 22589921, "name": " Doc Nirvana  ", "screen_name": "wstein"}, {"id": 327038661, "name": "\u2665  \u0e3fOSS\u0e3fITCH\u20a6ATION \u2665", "screen_name": "imCHOKOLATEwhoU"}, {"id": 19250651, "name": "Terri Weaver", "screen_name": "SoDear2MyHeart"}, {"id": 16506186, "name": "#LowSec", "screen_name": "sscoop4"}, {"id": 43924344, "name": "R0M0", "screen_name": "PyrexPress"}]}
