{"created_at": "Thu Oct 20 04:44:07 +0000 2011", "favorited": false, "hashtags": ["twitter", "DesahOgo"], "id": 126881358848065536, "id_str": "126881358848065536", "lang": "es", "retweeted": false, "source": "<a href=\"http://blackberry.com/twitter\" rel=\"nofollow\">Twitter for BlackBerry\u00ae</a>", "text": "#twitter Mii MediO de #DesahOgo..!!", "truncated": false, "user": {"created_at": "Mon Apr 18 13:07:15 +0000 2011", "description": "-| My everything? JerielG\u2661 |My wife? Cairis\u2661| Girla? Yianna\u2661 | Nito. Adrian\u2661| StayStrong \u2661| Believe in yourself\u2665|", "favourites_count": 13, "followers_count": 896, "friends_count": 829, "geo_enabled": true, "id": 284011232, "lang": "es", "listed_count": 5, "location": "-I\u2661God \u2665", "name": "-GabrielaAlcantara\u2665", "profile_background_color": "0A0A0A", "profile_background_image_url": "http://pbs.twimg.com/profile_background_images/378800000076708258/5b88b66270ef7ffb391d4e5240c26693.png", "profile_background_tile": true, "profile_banner_url": "https://pbs.twimg.com/profile_banners/284011232/1388254300", "profile_image_url": "https://pbs.twimg.com/profile_images/452285880095752192/vrg6nc6d_normal.jpeg", "profile_link_color": "ED07B0", "profile_sidebar_fill_color": "7AC3EE", "profile_text_color": "3D1957", "protected": false, "screen_name": "GabyAlcantara02", "statuses_count": 64344, "time_zone": "La Paz", "utc_offset": -14400}}
