{"created_at": "Thu Oct 20 03:31:56 +0000 2011", "favorited": false, "hashtags": ["Twitter"], "id": 126863190691811328, "id_str": "126863190691811328", "lang": "en", "retweeted": false, "source": "web", "text": "Man i love #Twitter!!", "truncated": false, "user": {"created_at": "Thu Oct 08 02:46:34 +0000 2009", "description": "You want to know just ask!!", "favourites_count": 21, "followers_count": 545, "friends_count": 895, "id": 80747685, "lang": "en", "name": "Moe", "profile_background_color": "131516", "profile_background_image_url": "http://pbs.twimg.com/profile_background_images/825151481/d27e052005166e8a43e6884a5c054732.jpeg", "profile_background_tile": true, "profile_image_url": "https://pbs.twimg.com/profile_images/3134525606/d9b6d44c800349d599449afcb0567a9f_normal.jpeg", "profile_link_color": "009999", "profile_sidebar_fill_color": "EFEFEF", "profile_text_color": "333333", "protected": false, "screen_name": "MR_MoJohnson", "statuses_count": 11304, "time_zone": "Central Time (US & Canada)", "utc_offset": -18000}}
