{"created_at": "Thu Oct 20 04:49:07 +0000 2011", "favorited": false, "hashtags": ["twitter", "news"], "id": 126882613569912832, "id_str": "126882613569912832", "lang": "en", "retweeted": false, "source": "<a href=\"http://twitterfeed.com\" rel=\"nofollow\">twitterfeed</a>", "text": "Chavez to return to Venezuela after medical tests - Boston Globe  #twitter #news", "truncated": false, "user": {"created_at": "Mon Jul 18 16:16:56 +0000 2011", "description": "Hello! You must see this http://t.co/detJInIFK1 ! \r\nWelcome to my blog $-)", "followers_count": 1148, "friends_count": 478, "id": 337805918, "lang": "en", "listed_count": 9, "location": "Ukraine", "name": "Ivan Egorov", "profile_background_color": "131516", "profile_background_image_url": "http://abs.twimg.com/images/themes/theme14/bg.gif", "profile_background_tile": true, "profile_image_url": "https://pbs.twimg.com/profile_images/1449265139/01_normal.jpg", "profile_link_color": "009999", "profile_sidebar_fill_color": "EFEFEF", "profile_text_color": "333333", "protected": false, "screen_name": "the1001news", "statuses_count": 43859, "time_zone": "Quito", "url": "http://t.co/49aN99k2Pn", "utc_offset": -18000}}
