{"created_at": "Thu Oct 20 03:55:27 +0000 2011", "favorited": false, "hashtags": ["Twitter"], "id": 126869110901575680, "id_str": "126869110901575680", "lang": "es", "retweet_count": 1, "retweeted": false, "source": "<a href=\"http://www.snaptu.com\" rel=\"nofollow\">Snaptu</a>", "text": "RT @Yonopienso_: RT @Yvandavid: Que lo mataron por #Twitter ya RT @Yonopienso_: \u00bfQue le paso a Osmel?xD.", "truncated": false, "user": {"created_at": "Sun May 08 18:49:09 +0000 2011", "favourites_count": 362, "followers_count": 3815, "friends_count": 4084, "geo_enabled": true, "id": 295292645, "lang": "es", "listed_count": 6, "name": "jose angel virgen", "profile_background_color": "ACDED6", "profile_background_image_url": "http://abs.twimg.com/images/themes/theme18/bg.gif", "profile_background_tile": false, "profile_image_url": "https://pbs.twimg.com/profile_images/2667654852/fccd61e42c7d9e8b94dbf11357cacc22_normal.jpeg", "profile_link_color": "038543", "profile_sidebar_fill_color": "F6F6F6", "profile_text_color": "333333", "protected": false, "screen_name": "Anyelius12", "statuses_count": 30453}, "user_mentions": [{"id": 520603330, "name": "Lorelis Salcedo", "screen_name": "YoNoPienso_"}, {"id": 122265994, "name": "Yirluys and Yvan\u2122", "screen_name": "Yvandavid"}, {"id": 520603330, "name": "Lorelis Salcedo", "screen_name": "YoNoPienso_"}]}
